Metadata-Version: 1.1
Name: search-in-files
Version: 0.0.6
Summary: A tool for find text in files.
Home-page: https://github.com/danielgatis/search_in_files
Author: Daniel Gatis
Author-email: danielgatis@gmail.com
License: MIT
Keywords: python file-search text-search fast
Platform: UNKNOWN
Classifier: Development Status :: 3 - Alpha
Classifier: Intended Audience :: Developers
Classifier: Topic :: Software Development :: Build Tools
Classifier: License :: OSI Approved :: MIT License
Classifier: Programming Language :: Python :: 2.7
Classifier: Programming Language :: Python :: 3
